pytest_yls/__init__.py
pytest_yls/plugin.py
pytest_yls/py.typed
pytest_yls/utils.py
pytest_yls-1.4.4.dist-info/LICENSE
pytest_yls-1.4.4.dist-info/METADATA
pytest_yls-1.4.4.dist-info/WHEEL
pytest_yls-1.4.4.dist-info/entry_points.txt
pytest_yls-1.4.4.dist-info/RECORD
