Metadata-Version: 2.3
Name: pytest-yls
Version: 1.4.4
Summary: Pytest plugin to test the YLS as a whole.
License: MIT
Author: Matej Kastak
Author-email: matej.kastak@avast.com
Maintainer: Matej Kašťák
Maintainer-email: matej.kastak@avast.com
Requires-Python: >=3.8,<4.0
Classifier: License :: OSI Approved :: MIT License
Classifier: Programming Language :: Python :: 3
Classifier: Programming Language :: Python :: 3.8
Classifier: Programming Language :: Python :: 3.9
Classifier: Programming Language :: Python :: 3.10
Classifier: Programming Language :: Python :: 3.11
Classifier: Programming Language :: Python :: 3.12
Classifier: Programming Language :: Python :: 3.13
Requires-Dist: pytest (>=8.3.3,<9.0.0)
Requires-Dist: tenacity (>=9.0.0,<10.0.0)
